{
  "id": 22864,
  "username": "cmunoz",
  "resource_state": 3,
  "firstname": "César",
  "lastname": "Muñoz",
  "city": "New York",
  "state": "New York",
  "country": "United States",
  "sex": "M",
  "premium": true,
  "created_at": "2011-04-10T15:37:53Z",
  "updated_at": "2017-05-08T12:49:12Z",
  "badge_type_id": 1,
  "profile_medium": "https://dgalywyr863hv.cloudfront.net/pictures/athletes/22864/12661/3/medium.jpg",
  "profile": "https://dgalywyr863hv.cloudfront.net/pictures/athletes/22864/12661/3/large.jpg",
  "friend": null,
  "follower": null,
  "follower_count": 23,
  "friend_count": 32,
  "mutual_friend_count": 0,
  "athlete_type": 0,
  "date_preference": "%m/%d/%Y",
  "measurement_preference": "feet",
  "clubs": [
    {
      "id": 193094,
      "resource_state": 2,
      "name": "Levi's® Commuter™",
      "profile_medium": "https://dgalywyr863hv.cloudfront.net/pictures/clubs/193094/4485587/2/medium.jpg",
      "profile": "https://dgalywyr863hv.cloudfront.net/pictures/clubs/193094/4485587/2/large.jpg",
      "cover_photo": "https://dgalywyr863hv.cloudfront.net/pictures/clubs/193094/4482922/22/large.jpg",
      "cover_photo_small": "https://dgalywyr863hv.cloudfront.net/pictures/clubs/193094/4482922/22/small.jpg",
      "sport_type": "cycling",
      "city": "San Francisco",
      "state": "California",
      "country": "United States",
      "private": false,
      "member_count": 402,
      "featured": false,
      "verified": true,
      "url": "LevisCommuter"
    },
    {
      "id": 272397,
      "resource_state": 2,
      "name": "AKQA NY",
      "profile_medium": "avatar/club/medium.png",
      "profile": "avatar/club/large.png",
      "cover_photo": null,
      "cover_photo_small": null,
      "sport_type": "cycling",
      "city": "Las Vegas",
      "state": "Nevada",
      "country": "United States",
      "private": false,
      "member_count": 1,
      "featured": false,
      "verified": false,
      "url": "akqany"
    }
  ],
  "email": "cesar.t.munoz@gmail.com",
  "ftp": null,
  "weight": 71.6676,
  "bikes": [
    {
      "id": "b837075",
      "primary": false,
      "name": "Bigshot",
      "resource_state": 2,
      "distance": 84317
    },
    {
      "id": "b25164",
      "primary": true,
      "name": "Pedal Force QS",
      "resource_state": 2,
      "distance": 8335077
    }
  ],
  "shoes": []
}